[
  {
    "timestamp": "2026-05-16T06:40:16.462835",
    "event": "catch_all",
    "chat_id": 7385595817,
    "chat_title": "harry",
    "detail": "content_type=text"
  },
  {
    "timestamp": "2026-05-16T06:40:18.877196",
    "event": "catch_all",
    "chat_id": 7385595817,
    "chat_title": "harry",
    "detail": "content_type=text"
  },
  {
    "timestamp": "2026-05-16T06:40:40.334596",
    "event": "catch_all",
    "chat_id": -1003745613477,
    "chat_title": "UPSC IMPORTANT",
    "detail": "content_type=text"
  },
  {
    "timestamp": "2026-05-16T06:40:55.596581",
    "event": "catch_all",
    "chat_id": 7385595817,
    "chat_title": "harry",
    "detail": "content_type=text"
  },
  {
    "timestamp": "2026-05-16T06:41:37.442311",
    "event": "catch_all",
    "chat_id": 7385595817,
    "chat_title": "harry",
    "detail": "content_type=text"
  },
  {
    "timestamp": "2026-05-16T06:41:39.637672",
    "event": "catch_all",
    "chat_id": 7385595817,
    "chat_title": "harry",
    "detail": "content_type=text"
  },
  {
    "timestamp": "2026-05-16T06:41:45.706476",
    "event": "catch_all",
    "chat_id": 7385595817,
    "chat_title": "harry",
    "detail": "content_type=text"
  },
  {
    "timestamp": "2026-05-16T06:44:29.551540",
    "event": "catch_all",
    "chat_id": 7385595817,
    "chat_title": "harry",
    "detail": "content_type=text"
  },
  {
    "timestamp": "2026-05-16T06:45:30.630075",
    "event": "catch_all",
    "chat_id": 7385595817,
    "chat_title": "harry",
    "detail": "content_type=text"
  },
  {
    "timestamp": "2026-05-16T06:46:16.146506",
    "event": "catch_all",
    "chat_id": -1003505989863,
    "chat_title": "BACKUP",
    "detail": "content_type=text"
  },
  {
    "timestamp": "2026-05-16T06:47:55.113242",
    "event": "catch_all",
    "chat_id": -1003505989863,
    "chat_title": "BACKUP",
    "detail": "content_type=text"
  },
  {
    "timestamp": "2026-05-16T06:51:36.902160",
    "event": "catch_all",
    "chat_id": -1003505989863,
    "chat_title": "BACKUP",
    "detail": "content_type=text"
  },
  {
    "timestamp": "2026-05-16T06:51:43.929435",
    "event": "catch_all",
    "chat_id": 7385595817,
    "chat_title": "harry",
    "detail": "content_type=text"
  },
  {
    "timestamp": "2026-05-16T06:52:28.596993",
    "event": "catch_all",
    "chat_id": 7385595817,
    "chat_title": "harry",
    "detail": "content_type=text"
  }
]